[
    {
        "garden": "WBTC",
        "token_value": 20048,
        "collateral": 0.19890088,
        "collateral_value": 3987.56484224,
        "borrowed": 9399.474074370844
    },
    {
        "garden": "NEAR",
        "token_value": 4.29,
        "collateral": 1584.0908918068287,
        "collateral_value": 6795.749925851295,
        "borrowed": 14564.847873873907
    },
    {
        "garden": "USDC",
        "token_value": 0.999528,
        "collateral": 25108.33653,
        "collateral_value": 25096.48539515784,
        "borrowed": 20012.96748600005
    },
    {
        "garden": "USDT",
        "token_value": 0.999872,
        "collateral": 112525.727746,
        "collateral_value": 112511.32445284851,
        "borrowed": 96438.10594093513
    },
    {
        "garden": "WETH",
        "token_value": 1553.1,
        "collateral": 7.8827020698796515,
        "collateral_value": 12242.624584730085,
        "borrowed": 11635.238496681048
    },
    {
        "garden": "UST",
        "token_value": 0.03149623,
        "collateral": 886.8329265711961,
        "collateral_value": 27.931893826859504,
        "borrowed": 27424.69481366437
    },
    {
        "total_borrowed": 179475.32868552534,
        "total_collateral_value": 160661.6810946546,
        "total_collateralization_ratio": 0.8951741850611914
    }
]