[
    {
        "garden": "WBTC",
        "token_value": 19131.53,
        "collateral": 0.19890088,
        "collateral_value": 3805.2781527464,
        "borrowed": 9399.474074370844
    },
    {
        "garden": "NEAR",
        "token_value": 3.0,
        "collateral": 1649.5985618501454,
        "collateral_value": 4948.795685550436,
        "borrowed": 14602.16085276101
    },
    {
        "garden": "USDC",
        "token_value": 0.999217,
        "collateral": 13836.952465,
        "collateral_value": 13826.118131219906,
        "borrowed": 9825.737032840174
    },
    {
        "garden": "USDT",
        "token_value": 0.99947,
        "collateral": 51506.325042,
        "collateral_value": 51479.02668972773,
        "borrowed": 42338.17588530721
    },
    {
        "garden": "WETH",
        "token_value": 1287.79,
        "collateral": 7.879691892352789,
        "collateral_value": 10147.388422052998,
        "borrowed": 9998.346921267417
    },
    {
        "garden": "UST",
        "token_value": 0.04279957,
        "collateral": 886.8329265711961,
        "collateral_value": 37.956067919088774,
        "borrowed": 27424.69481366437
    },
    {
        "total_borrowed": 113588.58958021103,
        "total_collateral_value": 84244.56314921657,
        "total_collateralization_ratio": 0.7416639599149785
    }
]