[
    {
        "garden": "WBTC",
        "token_value": 21085,
        "collateral": 0.19890088,
        "collateral_value": 4193.8250548,
        "borrowed": 9399.474074370844
    },
    {
        "garden": "NEAR",
        "token_value": 4.58,
        "collateral": 2184.0908918068285,
        "collateral_value": 10003.136284475275,
        "borrowed": 15071.580287207027
    },
    {
        "garden": "USDC",
        "token_value": 1.003,
        "collateral": 25369.366414,
        "collateral_value": 25445.474513241996,
        "borrowed": 20256.660075962107
    },
    {
        "garden": "USDT",
        "token_value": 1.003,
        "collateral": 82525.727746,
        "collateral_value": 82773.304929238,
        "borrowed": 70640.21453686415
    },
    {
        "garden": "WETH",
        "token_value": 1595.16,
        "collateral": 7.8827020698796515,
        "collateral_value": 12574.171033789225,
        "borrowed": 11635.238496681048
    },
    {
        "garden": "UST",
        "token_value": 0.04659513,
        "collateral": 886.8329265711961,
        "collateral_value": 41.322095501865334,
        "borrowed": 27424.69481366437
    },
    {
        "total_borrowed": 154427.86228474954,
        "total_collateral_value": 135031.23391104638,
        "total_collateralization_ratio": 0.8743968343100048
    }
]