[
    {
        "garden": "WBTC",
        "token_value": 20749,
        "collateral": 0.19890088,
        "collateral_value": 4126.99435912,
        "borrowed": 9399.474074370844
    },
    {
        "garden": "NEAR",
        "token_value": 3.13,
        "collateral": 1614.5985618501454,
        "collateral_value": 5053.693498590955,
        "borrowed": 14610.32496223515
    },
    {
        "garden": "USDC",
        "token_value": 0.998799,
        "collateral": 13572.831006,
        "collateral_value": 13556.530035961794,
        "borrowed": 9577.928515789761
    },
    {
        "garden": "USDT",
        "token_value": 0.999726,
        "collateral": 51507.325042,
        "collateral_value": 51493.212034938486,
        "borrowed": 42360.16949778753
    },
    {
        "garden": "WETH",
        "token_value": 1622.71,
        "collateral": 7.4218581310500396,
        "collateral_value": 12043.52340783621,
        "borrowed": 9805.957770936093
    },
    {
        "garden": "UST",
        "token_value": 0.03807629,
        "collateral": 886.8329265711961,
        "collateral_value": 33.767307693673565,
        "borrowed": 27424.69481366437
    },
    {
        "total_borrowed": 113178.54963478376,
        "total_collateral_value": 86307.72064414113,
        "total_collateralization_ratio": 0.7625801967126085
    }
]