[
    {
        "garden": "WBTC",
        "token_value": 24044,
        "collateral": 0.00061021,
        "collateral_value": 14.67188924,
        "borrowed": 6398.438806644557
    },
    {
        "garden": "NEAR",
        "token_value": 2.51,
        "collateral": 1007.1062445482767,
        "collateral_value": 2527.8366738161744,
        "borrowed": 14036.03802444452
    },
    {
        "garden": "USDC",
        "token_value": 0.99798,
        "collateral": 9999.811259,
        "collateral_value": 9979.61164025682,
        "borrowed": 6460.861522124529
    },
    {
        "garden": "USDT",
        "token_value": 0.998396,
        "collateral": 33.417495,
        "collateral_value": 33.36389333802,
        "borrowed": 6.755353930129434
    },
    {
        "garden": "WETH",
        "token_value": 1661.56,
        "collateral": 7.4218581310500396,
        "collateral_value": 12331.862596227504,
        "borrowed": 9805.957770936093
    },
    {
        "garden": "UST",
        "token_value": 0.02642624,
        "collateral": 886.8329265711961,
        "collateral_value": 23.435659757472806,
        "borrowed": 27424.69481366437
    },
    {
        "total_borrowed": 64132.746291744195,
        "total_collateral_value": 24910.782352635993,
        "total_collateralization_ratio": 0.3884253176889566
    }
]
