[
    {
        "garden": "WBTC",
        "token_value": 21597,
        "collateral": 0.19890088,
        "collateral_value": 4295.66230536,
        "borrowed": 9399.474074370844
    },
    {
        "garden": "NEAR",
        "token_value": 3.75,
        "collateral": 2435.384966568261,
        "collateral_value": 9132.693624630978,
        "borrowed": 16414.36499666071
    },
    {
        "garden": "USDC",
        "token_value": 1.002,
        "collateral": 125610.473043,
        "collateral_value": 125861.69398908601,
        "borrowed": 108644.237952067
    },
    {
        "garden": "USDT",
        "token_value": 0.999488,
        "collateral": 194505.884746,
        "collateral_value": 194406.29773301005,
        "borrowed": 159106.79361286396
    },
    {
        "garden": "WETH",
        "token_value": 1219.23,
        "collateral": 7.869889180887471,
        "collateral_value": 9595.204986013432,
        "borrowed": 11465.9829007232
    },
    {
        "garden": "UST",
        "token_value": 0.04815194,
        "collateral": 886.8329265711961,
        "collateral_value": 42.70272587028064,
        "borrowed": 27424.69481366437
    },
    {
        "total_borrowed": 332455.54835035,
        "total_collateral_value": 343334.25536397076,
        "total_collateralization_ratio": 1.0327222904463502
    }
]