[
    {
        "garden": "WBTC",
        "token_value": 20900,
        "collateral": 0.20038764,
        "collateral_value": 4188.101676,
        "borrowed": 9420.63939359077
    },
    {
        "garden": "NEAR",
        "token_value": 3.72,
        "collateral": 2514.270432179841,
        "collateral_value": 9353.08600770901,
        "borrowed": 16408.91547463699
    },
    {
        "garden": "USDC",
        "token_value": 1.003,
        "collateral": 162862.392276,
        "collateral_value": 163350.97945282797,
        "borrowed": 137227.434213192
    },
    {
        "garden": "USDT",
        "token_value": 1.001,
        "collateral": 194531.665379,
        "collateral_value": 194726.197044379,
        "borrowed": 158989.1405255352
    },
    {
        "garden": "WETH",
        "token_value": 1150.48,
        "collateral": 8.88261232221259,
        "collateral_value": 10219.267824459143,
        "borrowed": 11469.329692621077
    },
    {
        "garden": "UST",
        "token_value": 0.00899773,
        "collateral": 2686.8547734123044,
        "collateral_value": 24.175593800375097,
        "borrowed": 27365.51047066501
    },
    {
        "total_borrowed": 360880.96977024106,
        "total_collateral_value": 381861.8075991755,
        "total_collateralization_ratio": 1.0581378337635596
    }
]