[
    {
        "pool_name": "Stables Pool",
        "daily_volume": "6660.0899361070508773185"
    },
    {
        "pool_name": "Frax Pool",
        "daily_volume": "20341.1088392506542387375"
    },
    {
        "pool_name": "UST Pool",
        "daily_volume": "12438.297782729621381491"
    },
    {
        "pool_name": "BUSD Pool",
        "daily_volume": "6585.1823654138827322935"
    },
    {
        "pool_name": "MAI Pool",
        "daily_volume": "223.4842416787013189575"
    },
    {
        "pool_name": "RUSD Pool",
        "daily_volume": "1086.458918046829099026"
    }
]